{
	"config": {
		"step": {
			"user": {
				"title": "Aladin online (Czech Republic)",
				"data": {
					"name": "Name",
					"latitude": "Latitude",
					"longitude": "Longitude"
				}
			}
		},
		"abort": {
			"already_configured": "Aladin online for this name is already configured.",
			"service_unavailable": "Service is not available.",
			"location_unavailable": "Location is not available."
		}
	},
	"entity": {
		"sensor": {
			"apparent_temperature": {
				"name": "Apparent temperature"
			},
			"clouds": {
				"name": "Clouds"
			},
			"humidity": {
				"name": "Humidity"
			},
			"precipitation": {
				"name": "Precipitation intensity"
			},
			"pressure": {
				"name": "Pressure"
			},
			"snow_precipitation": {
				"name": "Snow precipitation"
			},
			"temperature": {
				"name": "Temperature"
			},
			"wind_speed": {
				"name": "Wind speed"
			},
			"wind_gust_speed": {
				"name": "Wind gust speed"
			}
		}
	}
}
